pyanty/__init__.py
pyanty/api.py
pyanty/ccl_leveldb.py
pyanty/ccl_simplesnappy.py
pyanty/pyanty.py
pyanty/utils.py
pyanty-1.1.0.dist-info/licenses/LICENSE
pyanty-1.1.0.dist-info/METADATA
pyanty-1.1.0.dist-info/WHEEL
pyanty-1.1.0.dist-info/top_level.txt
pyanty-1.1.0.dist-info/RECORD
