Metadata-Version: 2.4
Name: pyanty
Version: 1.1.0
Summary: Python module for controlling Dolphin browser profiles using Selenium, Pyppeteer, and Playwright. Includes Dolphin API for profile management.
Home-page: https://github.com/DedInc/pyanty
Author: Maehdakvan
Author-email: visitanimation@google.com
Project-URL: Bug Tracker, https://github.com/DedInc/pyanty/issues
Classifier: Programming Language :: Python :: 3
Classifier: License :: OSI Approved :: MIT License
Classifier: Operating System :: Microsoft :: Windows
Classifier: Operating System :: POSIX :: Linux
Classifier: Operating System :: MacOS
Requires-Python: >=3.6
License-File: LICENSE
Requires-Dist: requests
Requires-Dist: selenium
Requires-Dist: pywinauto
Dynamic: author
Dynamic: author-email
Dynamic: classifier
Dynamic: description
Dynamic: description-content-type
Dynamic: home-page
Dynamic: license-file
Dynamic: project-url
Dynamic: requires-dist
Dynamic: requires-python
Dynamic: summary
